cortado_marker/__init__.py
cortado_marker/data.py
cortado_marker/evaluate.py
cortado_marker/hill_climbing.py
cortado_marker/marker_genes.py
cortado_marker/utils.py
cortado_marker-0.1.4.dist-info/LICENSE
cortado_marker-0.1.4.dist-info/METADATA
cortado_marker-0.1.4.dist-info/WHEEL
cortado_marker-0.1.4.dist-info/top_level.txt
cortado_marker-0.1.4.dist-info/RECORD
